pykokoro/__init__.py
pykokoro/_version.py
pykokoro/audio_generator.py
pykokoro/constants.py
pykokoro/exceptions.py
pykokoro/generation_config.py
pykokoro/mixed_language_handler.py
pykokoro/onnx_backend.py
pykokoro/onnx_session.py
pykokoro/phoneme_dictionary.py
pykokoro/pipeline.py
pykokoro/pipeline_config.py
pykokoro/prosody.py
pykokoro/provider_config.py
pykokoro/say_as.py
pykokoro/short_sentence_handler.py
pykokoro/ssmd_parser.py
pykokoro/tokenizer.py
pykokoro/transcript.py
pykokoro/trim.py
pykokoro/types.py
pykokoro/utils.py
pykokoro/voice_manager.py
pykokoro/debug/__init__.py
pykokoro/debug/segment_invariants.py
pykokoro/runtime/__init__.py
pykokoro/runtime/cache.py
pykokoro/runtime/spans.py
pykokoro/runtime/tracing.py
pykokoro/stages/__init__.py
pykokoro/stages/protocols.py
pykokoro/stages/audio_generation/__init__.py
pykokoro/stages/audio_generation/base.py
pykokoro/stages/audio_generation/noop.py
pykokoro/stages/audio_generation/onnx.py
pykokoro/stages/audio_postprocessing/__init__.py
pykokoro/stages/audio_postprocessing/base.py
pykokoro/stages/audio_postprocessing/noop.py
pykokoro/stages/audio_postprocessing/onnx.py
pykokoro/stages/doc_parsers/__init__.py
pykokoro/stages/doc_parsers/plain.py
pykokoro/stages/doc_parsers/ssmd.py
pykokoro/stages/g2p/__init__.py
pykokoro/stages/g2p/base.py
pykokoro/stages/g2p/kokorog2p.py
pykokoro/stages/g2p/noop.py
pykokoro/stages/phoneme_processing/__init__.py
pykokoro/stages/phoneme_processing/base.py
pykokoro/stages/phoneme_processing/noop.py
pykokoro/stages/phoneme_processing/onnx.py
pykokoro/stages/synth/__init__.py
pykokoro/stages/synth/base.py
pykokoro/stages/synth/noop.py
pykokoro/stages/synth/onnx.py
pykokoro-0.6.4.dist-info/licenses/LICENSE
pykokoro-0.6.4.dist-info/METADATA
pykokoro-0.6.4.dist-info/WHEEL
pykokoro-0.6.4.dist-info/top_level.txt
pykokoro-0.6.4.dist-info/RECORD
