Metadata-Version: 2.4
Name: pykokoro
Version: 0.6.4
Summary: A python library for Kokoro TTS
Author-email: Holger Nahrstaedt <nahrstaedt@gmail.com>
License:                                  Apache License
Project-URL: Homepage, https://github.com/holgern/pykokoro
Keywords: tts,text-to-speech,kokoro,phonemizer,espeak
Classifier: Development Status :: 4 - Beta
Classifier: Intended Audience :: Developers
Classifier: Intended Audience :: Science/Research
Classifier: License :: OSI Approved :: Apache Software License
Classifier: Operating System :: OS Independent
Classifier: Programming Language :: Python :: 3
Classifier: Programming Language :: Python :: 3.10
Classifier: Programming Language :: Python :: 3.11
Classifier: Programming Language :: Python :: 3.12
Classifier: Programming Language :: Python :: 3.13
Classifier: Topic :: Multimedia :: Sound/Audio :: Speech
Classifier: Topic :: Scientific/Engineering :: Artificial Intelligence
Classifier: Topic :: Software Development :: Libraries :: Python Modules
Classifier: Topic :: Text Processing :: Linguistic
Requires-Python: >=3.10
License-File: LICENSE
Requires-Dist: kokorog2p[en,espeak]>=0.6.4
Requires-Dist: phrasplit>=0.3.1
Requires-Dist: numpy
Requires-Dist: onnxruntime>=1.17.0
Requires-Dist: platformdirs
Requires-Dist: chardet
Requires-Dist: charset-normalizer
Requires-Dist: huggingface-hub
Requires-Dist: ssmd>=0.7.1
Requires-Dist: num2words>=0.5.12
Requires-Dist: babel>=2.12.0
Requires-Dist: soundfile
Provides-Extra: dev
Requires-Dist: pytest>=7.0.0; extra == "dev"
Requires-Dist: pytest-cov>=4.0.0; extra == "dev"
Requires-Dist: ruff>=0.1.0; extra == "dev"
Requires-Dist: mypy>=1.0.0; extra == "dev"
Provides-Extra: prosody
Requires-Dist: audiomentations>=0.36.0; extra == "prosody"
Requires-Dist: librosa>=0.10.0; extra == "prosody"
Provides-Extra: gpu
Requires-Dist: onnxruntime-gpu>=1.17.0; extra == "gpu"
Provides-Extra: openvino
Requires-Dist: onnxruntime-openvino>=1.17.0; extra == "openvino"
Provides-Extra: directml
Requires-Dist: onnxruntime-directml>=1.17.0; extra == "directml"
Provides-Extra: coreml
Requires-Dist: coremltools>=7.0; extra == "coreml"
Provides-Extra: sounddevice
Requires-Dist: sounddevice; extra == "sounddevice"
Provides-Extra: all
Requires-Dist: onnxruntime-gpu>=1.17.0; extra == "all"
Requires-Dist: onnxruntime-openvino>=1.17.0; extra == "all"
Requires-Dist: onnxruntime-directml>=1.17.0; extra == "all"
Requires-Dist: coremltools>=7.0; extra == "all"
Requires-Dist: audiomentations>=0.36.0; extra == "all"
Requires-Dist: librosa>=0.10.0; extra == "all"
Requires-Dist: sounddevice; extra == "all"
Dynamic: license-file
